fsdag/__init__.py
fsdag/py.typed
fsdag-1.0.1.dist-info/LICENSE
fsdag-1.0.1.dist-info/METADATA
fsdag-1.0.1.dist-info/WHEEL
fsdag-1.0.1.dist-info/top_level.txt
fsdag-1.0.1.dist-info/RECORD
