Metadata-Version: 2.1
Name: fsdag
Version: 1.0.1
Summary: Simply define DAG-workflows in Python where artefacts are stored on a filesystem.
License: MIT License
Project-URL: repository, https://github.com/mristin/fsdag
Classifier: Development Status :: 5 - Production/Stable
Classifier: Intended Audience :: Developers
Classifier: License :: OSI Approved :: MIT License
Classifier: Programming Language :: Python :: 3
Classifier: Programming Language :: Python :: 3.8
Classifier: Programming Language :: Python :: 3.9
Classifier: Programming Language :: Python :: 3.10
Classifier: Programming Language :: Python :: 3.11
Classifier: Programming Language :: Python :: 3.12
Requires-Python: >=3.8
License-File: LICENSE
Provides-Extra: dev
Requires-Dist: black==24.8.0; extra == "dev"
Requires-Dist: mypy==1.13.0; extra == "dev"
Requires-Dist: pylint==3.2.7; extra == "dev"
Requires-Dist: coverage==7.6.1; extra == "dev"
